[{"date": "2023-09-12", "focus": "writing", "path": "https://notes.herson.xyz/Creative Practice/2023/09/2023-09-12.md"}, {"date": "2023-09-04", "focus": "writing", "path": "https://notes.herson.xyz/Creative Practice/2023/09/2023-09-04.md"}, {"date": "2023-09-21", "focus": "writing", "path": "https://notes.herson.xyz/Creative Practice/2023/09/2023-09-21.md"}, {"date": "2023-08-22", "focus": "av", "path": "https://notes.herson.xyz/Creative Practice/2023/08/2023-08-22.md"}, {"date": "2023-08-21", "focus": "av", "path": "https://notes.herson.xyz/Creative Practice/2023/08/2023-08-21.md"}]